tiberlogger/__init__.py
tiberlogger/display_logger.py
tiberlogger-1.1.4.dist-info/LICENSE
tiberlogger-1.1.4.dist-info/METADATA
tiberlogger-1.1.4.dist-info/WHEEL
tiberlogger-1.1.4.dist-info/top_level.txt
tiberlogger-1.1.4.dist-info/RECORD
