Metadata-Version: 2.1
Name: tiberlogger
Version: 1.1.4
Summary: Common logging routine for Tiber Health Python  scripts and appplications
Home-page: https://github.com/tiberhealth/TiberLogger
Author: Tiber Health Innovations
Author-email: tiber-tools@tiberhealth.com
License-File: LICENSE
